active_sample/__init__.py
active_sample/sampler.py
active_sample-0.0.2.data/data/LICENSE
active_sample-0.0.2.dist-info/METADATA
active_sample-0.0.2.dist-info/RECORD
active_sample-0.0.2.dist-info/WHEEL
active_sample-0.0.2.dist-info/top_level.txt
