Metadata-Version: 2.1
Name: active-sample
Version: 0.0.2
Summary: An active learning sampler
Home-page: https://github.com/billy4195/active_sample
Author: Billy Su
Author-email: g4691821@gmail.com
License: Apache License 2.0
Platform: UNKNOWN
Classifier: Programming Language :: Python :: 3
Classifier: License :: OSI Approved :: Apache Software License
Classifier: Operating System :: OS Independent
Requires-Python: >=3.6
